benford/__init__.py
benford/benford.py
benford_stats-0.0.6.dist-info/LICENSE
benford_stats-0.0.6.dist-info/METADATA
benford_stats-0.0.6.dist-info/WHEEL
benford_stats-0.0.6.dist-info/top_level.txt
benford_stats-0.0.6.dist-info/RECORD
