Metadata-Version: 2.1
Name: benford-stats
Version: 0.0.6
Summary: Statistical Test for Benfords Law
Home-page: https://gitlab.com/hbenne/benford/
Author: Hannes Benne
Author-email: hbenne@gmx.at
License: UNKNOWN
Project-URL: Bug Tracker, https://gitlab.com/hbenne/benford/issues
Platform: UNKNOWN
Classifier: Programming Language :: Python :: 3
Classifier: License :: OSI Approved :: MIT License
Classifier: Operating System :: OS Independent
Requires-Python: >=3.6
Requires-Dist: matplotlib
Requires-Dist: pandas
